{"elapsed":"54.092","endpoint-url":"https://services1.arcgis.com/ESMARspQHYMw9BZ9/arcgis/rest/services/Local_Planning_Authorities_April_2022_UK_BFE_2022/FeatureServer/0/query?outFields=*&where=1%3D1&f=geojson","entry-date":"2024-01-09T00:10:55.984664","request-headers":{"Accept":"*/*","Accept-Encoding":"gzip, deflate","Connection":"keep-alive","User-Agent":"DLUHC Digital Land"},"resource":"945ed334649c7514e7e24e5c7496652f286b08b014432fc56cd7506bc19308af","response-headers":{"Access-Control-Allow-Origin":"*","Cache-Control":"public, max-age=30, s-maxage=30","Connection":"keep-alive","Content-Encoding":"gzip","Content-Length":"75289889","Content-Type":"application/json; charset=utf-8","Date":"Tue, 09 Jan 2024 00:11:49 GMT","ETag":"sd14953_-347999372","Last-Modified":"Tue, 06 Dec 2022 10:30:26 GMT","Request-Context":"appId=cid-v1:02d88829-cd35-4b36-83db-f89bb9f85514","Vary":"X-Esri-Authorization","Via":"1.1 bd5ab138e49a090fd3089313c9c8105c.cloudfront.net (CloudFront)","X-Amz-Cf-Id":"pSJgxw1yeWdT0MW2aitxB_VsgUqZSB89w2Iy6iIwjH-C6b3EWEC78w==","X-Amz-Cf-Pop":"IAD12-P4","X-ArcGIS-Correlation-Id":"00-d21b2380dcc8d1d98ffdb2507c9f7e4d-6c761935cdcf6340-00","X-ArcGIS-Instance":"i7tdixsfq000007","X-ArcGIS-Trace-Id":"d21b2380dcc8d1d98ffdb2507c9f7e4d","X-Cache":"Miss from cloudfront","x-arcgis-upstream":"us1h01c00","x-esri-org-request-units-per-min":"usage=476;max=14400","x-esri-query-geometry-field-name":"Shape","x-esri-query-max-vertex-count":"381564","x-esri-query-readonly-replica":"true","x-esri-query-request-units":"2","x-esri-tiles-basic-query-mode":"true","x-esri-tiles-basic-query-type":"Basic"},"ssl-verify":true,"status":"200"}